django_snippet_image/__init__.py
django_snippet_image/attributes.py
django_snippet_image/conf.py
django_snippet_image/fields.py
django_snippet_image/sizes.py
django_snippet_image/validators.py
django_snippet_image-0.1.3.dist-info/LICENSE
django_snippet_image-0.1.3.dist-info/WHEEL
django_snippet_image-0.1.3.dist-info/METADATA
django_snippet_image-0.1.3.dist-info/RECORD
