Metadata-Version: 2.1
Name: django-snippet-image
Version: 0.1.3
Summary: Django field for create snippet image for sharing in social networks.
Home-page: https://github.com/acrius/django-snippet-image
License: MIT
Keywords: django,sharing,images,social,networks,snippets
Author: acrius
Author-email: acrius@mail.ru
Requires-Python: >=3.5,<4.0
Classifier: License :: OSI Approved :: MIT License
Classifier: Programming Language :: Python :: 3
Classifier: Programming Language :: Python :: 3.5
Classifier: Programming Language :: Python :: 3.6
Classifier: Programming Language :: Python :: 3.7
Requires-Dist: django (>=1.11,<3.0)
Requires-Dist: snippet-image (>=0.1.2,<0.2.0)
Project-URL: Repository, https://github.com/acrius/django-snippet-image
